LICENSE.txt
MANIFEST.in
README.rst
grole.py
setup.py
grole.egg-info/PKG-INFO
grole.egg-info/SOURCES.txt
grole.egg-info/dependency_links.txt
grole.egg-info/top_level.txt
test/helpers.py
test/test_args.py
test/test_grole.py
test/test_main.py
test/test_request.py
test/test_response.py
test/test_serve.py